qutewindow/Icon.py
qutewindow/__init__.py
qutewindow/platforms/__init__.py
qutewindow/platforms/mac/QuteDialog.py
qutewindow/platforms/mac/QuteMainWindow.py
qutewindow/platforms/mac/QuteWindow.py
qutewindow/platforms/mac/__init__.py
qutewindow/platforms/mac/title_bar/TitleBar.py
qutewindow/platforms/mac/utils.py
qutewindow/platforms/windows/QuteDialog.py
qutewindow/platforms/windows/QuteMainWindow.py
qutewindow/platforms/windows/QuteWindow.py
qutewindow/platforms/windows/__init__.py
qutewindow/platforms/windows/c_structures.py
qutewindow/platforms/windows/native_event.py
qutewindow/platforms/windows/title_bar/TitleBar.py
qutewindow/platforms/windows/title_bar/resources.qrc
qutewindow/platforms/windows/title_bar/resources_rc.py
qutewindow/platforms/windows/title_bar/title-bar/close.png
qutewindow/platforms/windows/title_bar/title-bar/close@2x.png
qutewindow/platforms/windows/title_bar/title-bar/close@3x.png
qutewindow/platforms/windows/title_bar/title-bar/maximize.png
qutewindow/platforms/windows/title_bar/title-bar/maximize@2x.png
qutewindow/platforms/windows/title_bar/title-bar/maximize@3x.png
qutewindow/platforms/windows/title_bar/title-bar/minimize.png
qutewindow/platforms/windows/title_bar/title-bar/minimize@2x.png
qutewindow/platforms/windows/title_bar/title-bar/minimize@3x.png
qutewindow/platforms/windows/title_bar/title-bar/restore.png
qutewindow/platforms/windows/title_bar/title-bar/restore@2x.png
qutewindow/platforms/windows/title_bar/title-bar/restore@3x.png
qutewindow/platforms/windows/utils.py
qutewindow-0.1.27.dist-info/METADATA
qutewindow-0.1.27.dist-info/WHEEL
qutewindow-0.1.27.dist-info/RECORD
